kedro_pandas_profiling/__init__.py
kedro_pandas_profiling/plugin.py
kedro_pandas_profiling-0.1.0.dist-info/LICENSE
kedro_pandas_profiling-0.1.0.dist-info/METADATA
kedro_pandas_profiling-0.1.0.dist-info/WHEEL
kedro_pandas_profiling-0.1.0.dist-info/entry_points.txt
kedro_pandas_profiling-0.1.0.dist-info/top_level.txt
kedro_pandas_profiling-0.1.0.dist-info/RECORD
